{
    "steph": {
        "password": "curry",
        "sections": {
            "nike": {
                "budget": "5000",
                "frequency": "35",
                "startDate": "32 june",
                "description": "my shoes",
                "purchases": {}
            }
        },
        "success": true
    },
    "draymond": {
        "password": "green",
        "sections": {}
    },
    "larry": {
        "password": "bird",
        "sections": {}
    },
    "michael": {
        "password": "jordan",
        "sections": {}
    }
}